taskinator/__init__.py
taskinator/__main__.py
taskinator/config.py
taskinator/mcp_server.py
taskinator/mcp_server_cli.py
taskinator/cli/__init__.py
taskinator/cli/commands.py
taskinator/cli/commands_original.py
taskinator/cli/init_command.py
taskinator/cli/commands/__init__.py
taskinator/cli/commands/add_bdd_scenario_command.py
taskinator/cli/commands/analyze_complexity_command.py
taskinator/cli/commands/create_prd_command.py
taskinator/cli/commands/discuss_command.py
taskinator/cli/commands/export_gherkin_command.py
taskinator/cli/commands/help_command.py
taskinator/cli/commands/import_gherkin_command.py
taskinator/cli/commands/list_command.py
taskinator/cli/commands/next_command.py
taskinator/cli/commands/pdd_command.py
taskinator/cli/commands/research_task_command.py
taskinator/cli/commands/set_status_command.py
taskinator/cli/commands/show_command.py
taskinator/cli/commands/sprint_commands.py
taskinator/cli/commands/stack_command.py
taskinator/cli/commands/story_commands.py
taskinator/cli/commands/sync_command.py
taskinator/core/__init__.py
taskinator/core/dependency_management.py
taskinator/core/file_storage.py
taskinator/core/file_storage_manager.py
taskinator/core/gherkin_exporter.py
taskinator/core/gherkin_importer.py
taskinator/core/prd_creation.py
taskinator/core/prd_templates.py
taskinator/core/sprint_manager.py
taskinator/core/story_point_systems.py
taskinator/core/story_processor.py
taskinator/core/task_expansion.py
taskinator/core/task_generation.py
taskinator/core/task_listing.py
taskinator/core/task_manager.py
taskinator/core/task_next.py
taskinator/core/task_status.py
taskinator/models/__init__.py
taskinator/models/sprint.py
taskinator/models/task.py
taskinator/models/validators.py
taskinator/plugins/__init__.py
taskinator/plugins/export_plugin.py
taskinator/plugins/integrations/__init__.py
taskinator/plugins/integrations/azure/__init__.py
taskinator/plugins/integrations/azure/client.py
taskinator/plugins/integrations/azure/commands.py
taskinator-0.2.2.dist-info/METADATA
taskinator-0.2.2.dist-info/WHEEL
taskinator-0.2.2.dist-info/entry_points.txt
taskinator-0.2.2.dist-info/top_level.txt
taskinator-0.2.2.dist-info/RECORD
