Metadata-Version: 2.4
Name: taskinator
Version: 0.2.2
Summary: A Python CLI task management tool for software development projects. Heavily inspired by claude-task-master
Author: Steve Smahnuk
Author-email: ssmashnuk@gmail.com
Classifier: Development Status :: 3 - Alpha
Classifier: Intended Audience :: Developers
Classifier: Programming Language :: Python :: 3
Classifier: Programming Language :: Python :: 3.9
Requires-Python: >=3.9
Requires-Dist: typer>=0.9.0
Requires-Dist: rich>=13.7.0
Requires-Dist: pydantic>=2.5.2
Requires-Dist: anthropic>=0.18.1
Requires-Dist: openai>=1.13.3
Requires-Dist: python-dotenv>=1.0.0
Requires-Dist: filelock>=3.12.0
Requires-Dist: litellm>=1.68.1
Requires-Dist: caldav>=1.3.0
Requires-Dist: tomli>=2.0.1
Provides-Extra: dev
Requires-Dist: black>=23.12.0; extra == "dev"
Requires-Dist: isort>=5.12.0; extra == "dev"
Requires-Dist: mypy>=1.7.1; extra == "dev"
Requires-Dist: pytest>=7.4.3; extra == "dev"
Requires-Dist: pytest-bdd>=7.1.1; extra == "dev"
Requires-Dist: flake8>=6.1.0; extra == "dev"
Provides-Extra: azure
Requires-Dist: azure-devops>=7.1.0; extra == "azure"
Provides-Extra: gitlab
Requires-Dist: python-gitlab>=4.4.0; extra == "gitlab"
Dynamic: author
Dynamic: author-email
Dynamic: classifier
Dynamic: provides-extra
Dynamic: requires-dist
Dynamic: requires-python
Dynamic: summary
